PyWebScraper/__init__.py
PyWebScraper/log.py
PyWebScraper/scraper.py
PyWebScraper-0.1.5.dist-info/LICENSE
PyWebScraper-0.1.5.dist-info/METADATA
PyWebScraper-0.1.5.dist-info/WHEEL
PyWebScraper-0.1.5.dist-info/top_level.txt
PyWebScraper-0.1.5.dist-info/RECORD
