Metadata-Version: 2.1
Name: PyWebScraper
Version: 0.1.5
Summary: A web scraper that combines both Beautiful Soup (bs4) and Selenium.
Home-page: https://github.com/glowingkitty/PyWebScraper
Author: Marco
License: UNKNOWN
Platform: UNKNOWN
Classifier: Programming Language :: Python :: 3
Classifier: License :: OSI Approved :: MIT License
Classifier: Operating System :: OS Independent
Requires-Python: >=3.6
Requires-Dist: bs4
Requires-Dist: requests
Requires-Dist: selenium
